vbayesfa/.DS_Store
vbayesfa/__init__.py
vbayesfa/bayes_factors.py
vbayesfa/exp_families.py
vbayesfa/finite_lpa.py
vbayesfa/fit_finite_lpa.py
vbayesfa/fit_lpa.py
vbayesfa/fit_lpa2.py
vbayesfa/fit_mixture_model.py
vbayesfa/lpa.py
vbayesfa/lpa_outcome_analysis.py
vbayesfa/mixture_model.py
vbayesfa/old_lpa.py
vbayesfa/simulate_data.py
vbayesfa/ibp/discrete_finite.py
vbayesfa/ibp/fit_ibp.py
vbayesfa/ibp/full_discrete_finite.py
vbayesfa/ibp/make_sim_data.py
vbayesfa/ibp/sparse_cont_finite.py
vbayesfa/ibp/sparse_pos_cont_finite.py
vbayesfa/tests/.DS_Store
vbayesfa/tests/test_exp_families.py
vbayesfa/tests/test_finite_lpa.py
vbayesfa/tests/test_lpa.py
vbayesfa/tests/test_lpa_outcome_analysis.py
vbayesfa-0.0.33.dist-info/WHEEL
vbayesfa-0.0.33.dist-info/METADATA
vbayesfa-0.0.33.dist-info/RECORD
