Metadata-Version: 2.1
Name: vbayesfa
Version: 0.0.33
Summary: Dirichlet process mixture models for latent profile analysis.
Author-email: Sam Paskewitz <samuel.paskewitz@yale.edu>
